{
  "parent": "minecraft:recipes/root",
  "rewards": {
    "recipes": [
      "neepmeat:yellow_rough_concrete"
    ]
  },
  "criteria": {
    "has_yellow_concrete": {
      "trigger": "minecraft:inventory_changed",
      "conditions": {
        "items": [
          {
            "items": [
              "minecraft:yellow_concrete"
            ]
          }
        ]
      }
    },
    "has_sand": {
      "trigger": "minecraft:inventory_changed",
      "conditions": {
        "items": [
          {
            "items": [
              "minecraft:sand"
            ]
          }
        ]
      }
    },
    "has_the_recipe": {
      "trigger": "minecraft:recipe_unlocked",
      "conditions": {
        "recipe": "neepmeat:yellow_rough_concrete"
      }
    }
  },
  "requirements": [
    [
      "has_yellow_concrete",
      "has_sand",
      "has_the_recipe"
    ]
  ]
}