{
	"credit": "Made with Blockbench",
	"textures": {
		"0": "neepmeat:block/fluid_exciter/window",
		"1": "neepmeat:block/fluid_exciter/base",
		"2": "neepmeat:block/fluid_exciter/bottom",
		"3": "neepmeat:block/fluid_exciter/base_top",
		"4": "neepmeat:block/fluid_exciter/dome",
		"particle": "neepmeat:block/fluid_exciter/window"
	},
	"elements": [
		{
			"from": [0.41421, 19, -0.24264],
			"to": [1.41421, 29, 4],
			"rotation": {"angle": -45, "axis": "y", "origin": [1.41421, 24, 3]},
			"faces": {
				"east": {"uv": [0, 6, 4, 16], "texture": "#4"},
				"west": {"uv": [12, 6, 16, 16], "texture": "#4"},
				"up": {"uv": [12, 6, 16, 7], "rotation": 90, "texture": "#4"}
			}
		},
		{
			"from": [15.92893, 19, 4.27208],
			"to": [16.92893, 29, 8.51472],
			"rotation": {"angle": -45, "axis": "y", "origin": [5.92893, 24, 7.51472]},
			"faces": {
				"east": {"uv": [12, 6, 16, 16], "texture": "#4"},
				"west": {"uv": [0, 6, 4, 16], "texture": "#4"},
				"up": {"uv": [12, 6, 16, 7], "rotation": 90, "texture": "#4"},
				"down": {"uv": [0, 0, 0.25, 1.06066], "texture": "#missing"}
			}
		},
		{
			"from": [1.35355, 19, 12.02513],
			"to": [2.35355, 29, 16.26777],
			"rotation": {"angle": 45, "axis": "y", "origin": [1.85355, 24, 14.14645]},
			"faces": {
				"east": {"uv": [0, 6, 4, 16], "texture": "#4"},
				"west": {"uv": [0, 6, 4, 16], "texture": "#4"},
				"up": {"uv": [12, 15, 16, 16], "rotation": 90, "texture": "#4"}
			}
		},
		{
			"from": [16.57538, 19, 6.8033],
			"to": [17.57538, 29, 11.04594],
			"rotation": {"angle": 45, "axis": "y", "origin": [7.07538, 24, 8.92462]},
			"faces": {
				"east": {"uv": [0, 6, 4, 16], "texture": "#4"},
				"west": {"uv": [0, 6, 4, 16], "texture": "#4"},
				"up": {"uv": [12, 15, 16, 16], "rotation": 90, "texture": "#4"}
			}
		},
		{
			"from": [3, 31, 3],
			"to": [13, 32, 13],
			"rotation": {"angle": 0, "axis": "y", "origin": [1, 24, 1]},
			"faces": {
				"up": {"uv": [3, 6, 13, 16], "rotation": 90, "texture": "#4"},
				"down": {"uv": [3, 6, 13, 16], "rotation": 90, "texture": "#4"}
			}
		},
		{
			"from": [3, 19.85786, 22.92893],
			"to": [13, 24.1005, 23.92893],
			"rotation": {"angle": -45, "axis": "x", "origin": [1, 14.85786, 8.92893]},
			"faces": {
				"north": {"uv": [0, 0, 10, 4], "texture": "#4"},
				"east": {"uv": [0, 0, 1, 4], "texture": "#4"},
				"south": {"uv": [0, 0, 10, 4], "texture": "#4"},
				"west": {"uv": [9, 0, 10, 4], "texture": "#4"}
			}
		},
		{
			"from": [12.15685, 23.55025, 3],
			"to": [13.15685, 27.79289, 13],
			"rotation": {"angle": 45, "axis": "z", "origin": [8, 29.70711, 8]},
			"faces": {
				"north": {"uv": [0, 0, 1, 4], "texture": "#4"},
				"east": {"uv": [0, 0, 10, 4], "texture": "#4"},
				"south": {"uv": [9, 0, 10, 4], "texture": "#4"},
				"west": {"uv": [0, 0, 10, 4], "texture": "#4"}
			}
		},
		{
			"from": [2.84315, 23.55025, 3],
			"to": [3.84315, 27.79289, 13],
			"rotation": {"angle": -45, "axis": "z", "origin": [8, 29.70711, 8]},
			"faces": {
				"north": {"uv": [9, 0, 10, 4], "texture": "#4"},
				"east": {"uv": [0, 0, 10, 4], "texture": "#4"},
				"south": {"uv": [0, 0, 1, 4], "texture": "#4"},
				"west": {"uv": [0, 0, 10, 4], "texture": "#4"}
			}
		},
		{
			"from": [3, 23.55025, 2.84315],
			"to": [13, 27.79289, 3.84315],
			"rotation": {"angle": 45, "axis": "x", "origin": [8, 29.70711, 8]},
			"faces": {
				"north": {"uv": [0, 0, 10, 4], "texture": "#4"},
				"east": {"uv": [0, 0, 1, 4], "texture": "#4"},
				"south": {"uv": [0, 0, 10, 4], "texture": "#4"},
				"west": {"uv": [9, 0, 10, 4], "texture": "#4"}
			}
		},
		{
			"from": [0, 19, 3],
			"to": [1, 29, 13],
			"rotation": {"angle": 0, "axis": "y", "origin": [8, 8, 8]},
			"faces": {
				"east": {"uv": [3, 6, 13, 16], "texture": "#4"},
				"west": {"uv": [3, 6, 13, 16], "texture": "#4"}
			}
		},
		{
			"from": [3, 19, 0],
			"to": [13, 29, 1],
			"rotation": {"angle": 0, "axis": "y", "origin": [8, 8, 8]},
			"faces": {
				"north": {"uv": [3, 6, 13, 16], "texture": "#4"},
				"south": {"uv": [3, 6, 13, 16], "texture": "#4"}
			}
		},
		{
			"from": [15, 19, 3],
			"to": [16, 29, 13],
			"rotation": {"angle": 0, "axis": "y", "origin": [8, 8, 8]},
			"faces": {
				"east": {"uv": [3, 6, 13, 16], "texture": "#4"},
				"west": {"uv": [3, 6, 13, 16], "texture": "#4"}
			}
		},
		{
			"from": [3, 19, 15],
			"to": [13, 29, 16],
			"rotation": {"angle": 0, "axis": "y", "origin": [8, 8, 8]},
			"faces": {
				"north": {"uv": [3, 6, 13, 16], "texture": "#4"},
				"south": {"uv": [3, 6, 13, 16], "texture": "#4"}
			}
		},
		{
			"from": [3, 19, 3],
			"to": [13, 30, 13],
			"rotation": {"angle": 0, "axis": "y", "origin": [1, 24, 1]},
			"faces": {
				"north": {"uv": [3, 5, 13, 16], "texture": "#4"},
				"east": {"uv": [3, 5, 13, 16], "texture": "#4"},
				"south": {"uv": [3, 5, 13, 16], "texture": "#4"},
				"west": {"uv": [3, 5, 13, 16], "texture": "#4"},
				"up": {"uv": [3, 6, 13, 16], "texture": "#4"}
			}
		},
		{
			"from": [0, 17, 0],
			"to": [16, 19, 16],
			"faces": {
				"north": {"uv": [0, 0, 16, 2], "texture": "#3"},
				"east": {"uv": [0, 0, 16, 2], "texture": "#3"},
				"south": {"uv": [0, 0, 16, 2], "texture": "#3"},
				"west": {"uv": [0, 0, 16, 2], "texture": "#3"},
				"up": {"uv": [0, 0, 16, 16], "texture": "#3"},
				"down": {"uv": [0, 0, 4, 4], "texture": "#3"}
			}
		},
		{
			"from": [0, 0, 0],
			"to": [16, 10, 16],
			"faces": {
				"north": {"uv": [0, 5, 16, 16], "texture": "#1"},
				"east": {"uv": [0, 5, 16, 16], "texture": "#1"},
				"south": {"uv": [0, 5, 16, 16], "texture": "#1"},
				"west": {"uv": [0, 5, 16, 16], "texture": "#1"},
				"up": {"uv": [0, 0, 16, 16], "texture": "#3"},
				"down": {"uv": [0, 0, 16, 16], "texture": "#2"}
			}
		},
		{
			"from": [0, 10, 3],
			"to": [2, 13, 13],
			"rotation": {"angle": 0, "axis": "y", "origin": [8, 10.5, 8]},
			"faces": {
				"north": {"uv": [14, 3, 16, 5], "texture": "#1"},
				"south": {"uv": [16, 3, 14, 5], "texture": "#1"},
				"west": {"uv": [3, 2, 13, 5], "texture": "#1"},
				"up": {"uv": [3, 3, 13, 1], "rotation": 270, "texture": "#1"}
			}
		},
		{
			"from": [3, 10, 14],
			"to": [13, 13, 16],
			"rotation": {"angle": 0, "axis": "y", "origin": [8, 10.5, 8]},
			"faces": {
				"east": {"uv": [16, 3, 14, 5], "texture": "#1"},
				"south": {"uv": [3, 2, 13, 5], "texture": "#1"},
				"west": {"uv": [14, 3, 16, 5], "texture": "#1"},
				"up": {"uv": [3, 3, 13, 1], "rotation": 180, "texture": "#1"}
			}
		},
		{
			"from": [3, 10, 0],
			"to": [13, 13, 2],
			"rotation": {"angle": 0, "axis": "y", "origin": [8, 10.5, 8]},
			"faces": {
				"north": {"uv": [3, 2, 13, 5], "texture": "#1"},
				"east": {"uv": [14, 3, 16, 5], "texture": "#1"},
				"west": {"uv": [16, 3, 14, 5], "texture": "#1"},
				"up": {"uv": [3, 3, 13, 1], "texture": "#1"}
			}
		},
		{
			"from": [14, 10, 3],
			"to": [16, 13, 13],
			"rotation": {"angle": 0, "axis": "y", "origin": [8, 10.5, 8]},
			"faces": {
				"north": {"uv": [16, 3, 14, 5], "texture": "#1"},
				"east": {"uv": [3, 2, 13, 5], "texture": "#1"},
				"south": {"uv": [14, 3, 16, 5], "texture": "#1"},
				"up": {"uv": [3, 3, 13, 1], "rotation": 90, "texture": "#1"}
			}
		},
		{
			"from": [1, 10, 1],
			"to": [15, 17, 15],
			"faces": {
				"north": {"uv": [0, 0, 14, 7], "texture": "#0"},
				"east": {"uv": [0, 0, 14, 7], "texture": "#0"},
				"south": {"uv": [0, 0, 14, 7], "texture": "#0"},
				"west": {"uv": [0, 0, 14, 7], "texture": "#0"}
			}
		},
		{
			"from": [2, 11, 2],
			"to": [14, 17, 14],
			"color": 5,
			"faces": {
				"north": {"uv": [0, 0, 3, 1.5], "texture": "#missing"},
				"east": {"uv": [0, 0, 3, 1.5], "texture": "#missing"},
				"south": {"uv": [0, 0, 3, 1.5], "texture": "#missing"},
				"west": {"uv": [0, 0, 3, 1.5], "texture": "#missing"},
				"up": {"uv": [0, 0, 3, 3], "texture": "#missing"},
				"down": {"uv": [0, 0, 3, 3], "texture": "#missing"}
			}
		}
	],
	"display": {
		"thirdperson_righthand": {
			"rotation": [75, 45, 0],
			"translation": [0, 2.5, 0],
			"scale": [0.375, 0.375, 0.375]
		},
		"thirdperson_lefthand": {
			"rotation": [75, 45, 0],
			"translation": [0, 2.5, 0],
			"scale": [0.375, 0.375, 0.375]
		},
		"firstperson_righthand": {
			"rotation": [0, 45, 0],
			"scale": [0.4, 0.4, 0.4]
		},
		"firstperson_lefthand": {
			"rotation": [0, 225, 0],
			"scale": [0.4, 0.4, 0.4]
		},
		"ground": {
			"translation": [0, 3, 0],
			"scale": [0.25, 0.25, 0.25]
		},
		"gui": {
			"rotation": [30, 225, 0],
			"translation": [0, -2.5, 0],
			"scale": [0.41602, 0.41602, 0.41602]
		},
		"fixed": {
			"scale": [0.5, 0.5, 0.5]
		}
	}
}